odoo/addons/hr_holidays_validity_date/README.rst
odoo/addons/hr_holidays_validity_date/__init__.py
odoo/addons/hr_holidays_validity_date/__manifest__.py
odoo/addons/hr_holidays_validity_date/i18n/ar.po
odoo/addons/hr_holidays_validity_date/i18n/cs_CZ.po
odoo/addons/hr_holidays_validity_date/i18n/de.po
odoo/addons/hr_holidays_validity_date/i18n/es.po
odoo/addons/hr_holidays_validity_date/i18n/fr.po
odoo/addons/hr_holidays_validity_date/i18n/hr.po
odoo/addons/hr_holidays_validity_date/i18n/hr_HR.po
odoo/addons/hr_holidays_validity_date/i18n/hr_holidays_validity_date.pot
odoo/addons/hr_holidays_validity_date/i18n/sl.po
odoo/addons/hr_holidays_validity_date/models/__init__.py
odoo/addons/hr_holidays_validity_date/models/hr_holidays.py
odoo/addons/hr_holidays_validity_date/readme/CONTRIBUTORS.rst
odoo/addons/hr_holidays_validity_date/readme/DESCRIPTION.rst
odoo/addons/hr_holidays_validity_date/static/description/icon.png
odoo/addons/hr_holidays_validity_date/static/description/index.html
odoo/addons/hr_holidays_validity_date/tests/__init__.py
odoo/addons/hr_holidays_validity_date/tests/test_hr_holidays_validity_date.py
odoo/addons/hr_holidays_validity_date/views/hr_holidays_view.xml
odoo11_addon_hr_holidays_validity_date-11.0.1.0.1.dist-info/METADATA
odoo11_addon_hr_holidays_validity_date-11.0.1.0.1.dist-info/WHEEL
odoo11_addon_hr_holidays_validity_date-11.0.1.0.1.dist-info/top_level.txt
odoo11_addon_hr_holidays_validity_date-11.0.1.0.1.dist-info/RECORD
